README.md
pyproject.toml
villas/__init__.py
villas/node/__init__.py
villas/node/communicate.py
villas/node/digest.py
villas/node/formats.py
villas/node/node.py
villas/node/opal_orchestra_ddf.py
villas/node/sample.py
villas/node/test_digest.py
villas/node/test_formats.py
villas/node/test_sample.py
villas/node/villas_pb2.py
villas/node/villas_pb2.pyi
villas_node.egg-info/PKG-INFO
villas_node.egg-info/SOURCES.txt
villas_node.egg-info/dependency_links.txt
villas_node.egg-info/entry_points.txt
villas_node.egg-info/requires.txt
villas_node.egg-info/top_level.txt