Metadata-Version: 2.4
Name: villas-node
Version: 1.1.0
Summary: Python support for the VILLASnode simulation-data gateway
Author-email: Steffen Vogel <post@steffenvogel.de>, Philipp Jungkamp <Philipp.Jungkamp@opal-rt.com>
Project-URL: GitHub, https://github.com/VILLASframework/node
Project-URL: Project, https://www.fein-aachen.org/en/projects/villas-node
Project-URL: Homepage, https://villas.fein-aachen.org
Keywords: simulation,power,system,real-time,villas
Classifier: Development Status :: 4 - Beta
Classifier: Topic :: Scientific/Engineering
Classifier: Operating System :: POSIX :: Linux
Classifier: Programming Language :: Python :: 3
Requires-Python: >=3.10
Requires-Dist: linuxfd==1.5; platform_system == "Linux"
Requires-Dist: protobuf==6.32.1
Requires-Dist: libconf==2.0.1
Provides-Extra: dev
Requires-Dist: black==25.11.0; extra == "dev"
Requires-Dist: flake8==7.3.0; extra == "dev"
Requires-Dist: mypy==1.19.0; extra == "dev"
Requires-Dist: pytest==9.0.1; extra == "dev"
Requires-Dist: types-protobuf==6.32.1.20251105; extra == "dev"
